{
  "ipos": {
    "status": "healthy",
    "updated_at": "2026-06-25T18:23:04.307746+00:00Z"
  },
  "fii_dii": {
    "status": "healthy",
    "updated_at": "2026-06-25T18:19:50.622130+00:00Z"
  },
  "corporate_actions": {
    "status": "healthy",
    "updated_at": "2026-06-25T18:19:51.343820+00:00Z"
  },
  "earnings_calendar": {
    "status": "healthy",
    "updated_at": "2026-06-25T18:19:51.924754+00:00Z"
  },
  "market_breadth": {
    "status": "healthy",
    "updated_at": "2026-06-25T18:22:46.903412+00:00Z"
  },
  "global_indices": {
    "status": "healthy",
    "updated_at": "2026-06-25T18:22:45.824663+00:00Z"
  },
  "high_low": {
    "status": "healthy",
    "updated_at": "2026-06-25T18:23:06.751474+00:00Z"
  },
  "sector_performance": {
    "status": "healthy",
    "updated_at": "2026-06-25T18:23:05.114357+00:00Z"
  },
  "market_sentiment": {
    "status": "healthy",
    "updated_at": "2026-06-25T18:23:05.537837+00:00Z"
  }
}